jsnac/__init__.py
jsnac/core/__init__.py
jsnac/core/build.py
jsnac/utils/__init__.py
jsnac/utils/jsnac_cli.py
jsnac-0.3.0.dist-info/METADATA
jsnac-0.3.0.dist-info/WHEEL
jsnac-0.3.0.dist-info/entry_points.txt
jsnac-0.3.0.dist-info/licenses/LICENSE
jsnac-0.3.0.dist-info/RECORD
