Metadata-Version: 2.4
Name: jsnac
Version: 0.3.0
Summary: JSON Schema (for) Network as Code: Build JSON schemas from YAML
Project-URL: Repository, https://github.com/commitconfirmed/jsnac
Author-email: Andrew Jones <jsnac@commitconfirmed.com>
License-Expression: MIT
License-File: LICENSE
Classifier: Programming Language :: Python :: 3.10
Classifier: Programming Language :: Python :: 3.11
Classifier: Programming Language :: Python :: 3.12
Classifier: Programming Language :: Python :: 3.13
Requires-Python: <4.0,>=3.11
Requires-Dist: pyyaml<7.0.0,>=6.0.2
